agent_api/__init__.py
agent_api/client.py
agent_api/models/__init__.py
agent_api/models/agents.py
agent_api/models/chat.py
agent_api/models/environment.py
agent_api/models/error_handling.py
agent_api/models/session.py
agent_api/models/task.py
agent_api/models/tools.py
agent_api/models/user.py
lyzr_agent_api/__init__.py
lyzr_agent_api/client.py
lyzr_agent_api/models/__init__.py
lyzr_agent_api/models/agents.py
lyzr_agent_api/models/chat.py
lyzr_agent_api/models/environment.py
lyzr_agent_api/models/error_handling.py
lyzr_agent_api/models/session.py
lyzr_agent_api/models/task.py
lyzr_agent_api/models/tools.py
lyzr_agent_api/models/user.py
lyzr_agent_api-0.1.0.dist-info/METADATA
lyzr_agent_api-0.1.0.dist-info/WHEEL
lyzr_agent_api-0.1.0.dist-info/top_level.txt
lyzr_agent_api-0.1.0.dist-info/RECORD
