Metadata-Version: 2.1
Name: lyzr-agent-api
Version: 0.1.0
Summary: Official client for Lyzr Agent API
Home-page: https://github.com/LyzrCore/lyzr-agent
Author: lyzr
License: UNKNOWN
Platform: UNKNOWN
Requires-Python: >=3.8.1, <3.12.5
Requires-Dist: httpx (==0.27.2)
